{
  "id": 191488,
  "name": "ニコニコ(Re)のマイページ(2020年10月版)を詰めるだけ",
  "description": "CSSぜんぜんわからん！勢なのでクオリティには期待しないで。\r\n予告なく大きな変更が入るかも&保守が放棄されるかも\r\n\r\n現状ニコレポ/フォロー/マイリスト/あとで見る/履歴画面に対応\r\n遅延ロードがウザい件についてはCSSじゃどうしようもないので、グリモンとか使ってJSで対応してください\r\n\r\nTips:\r\n- 左に寄り過ぎてるのが嫌！て人はコメントアウトしてある「全画面に最適化する用」がいいかも\r\n\r\nFeatures:\r\n- サムネを左に、アクティビティと動画タイトルをその右に\r\n- 各ニコレポなどの白地のアイテム(カード)を枠でくくって詰め詰めに\r\n- ほか、全体的に幅を詰める",
  "user": {
    "id": 1056102,
    "name": "gonbuto",
    "email": "redacted",
    "paypal_email": null,
    "homepage": null,
    "about": null,
    "license": null
  },
  "updated": "2020-10-28T09:33:00.000Z",
  "weekly_install_count": 24,
  "total_install_count": 24,
  "rating": null,
  "after_screenshot_name": "https://userstyles.org/style_screenshots/191488_after.png?r=1603877580",
  "obsoleting_style_id": null,
  "obsoleting_style_name": null,
  "obsolete": 0,
  "admin_delete_reason_id": null,
  "obsoletion_message": null,
  "screenshots": null,
  "license": "publicdomain",
  "created": "2020-10-27T09:30:02.000Z",
  "category": "site",
  "raw_subcategory": "nicovideo",
  "subcategory": "nicovideo",
  "additional_info": "2020/10/28: マイリスト、あとで見るリスト、履歴画面に仮対応",
  "style_tags": [],
  "css": "@-moz-document url-prefix(\"https://www.nicovideo.jp/my\"), url-prefix(\"https://www.nicovideo.jp/user/\") {\r\n  /********************************/\r\n /* ページトップのニコニコヘッダ */\r\n/********************************/\r\n.HeaderContainer_Re-main { height: 48px; }\r\n\r\n  /********************************/\r\n /* ページトップのユーザ名ヘッダ */\r\n/********************************/\r\n.UserDetailsHeader { padding-bottom: 0px; }\r\n\r\n\r\n  /*******************************/\r\n /* カードの横幅712px制限を解除 */\r\n/*******************************/\r\n.NicorepoPage-content { width: auto; }\r\n.HistoryPage-content { width: auto; }\r\n/* これをコメントアウトすれば他ページ同様の全枠になるが、動画説明文の長さは変わらないので見た目が不自然 */\r\n/* .MylistPage-content { width: inherit; } */\r\n\r\n/* 干渉する右サイドメニューを背面へ回しつつ右横へ避ける */\r\n/* 素直に消したほうが早いとは思うが一応 */\r\n.RightSideContainer { z-index: -1; margin-top: 172px; width: 200px; }\r\n.RightSideContainer * { height: auto; max-width: 200px; max-height: none; }\r\n.RightSideContainer a { display: block; }\r\n\r\n/* 全画面に最適化する用\r\n.UserPage-main { padding: 0 0 0 0; }　\r\n.RightSideContainer { z-index: -1; margin-top: 172px; margin-left: 635px; width: 200px; }\r\n*/\r\n\r\n\r\n  /**************************************************************/\r\n /* 白地枠なしカード(ニコレポ、マイリス、フォロー)に枠をつける */\r\n/**************************************************************/\r\n.NicorepoItem-item, .UserItem-content, .MylistMediaObject-linkArea {\r\n  padding: 4px;\r\n  border: 1px solid #000;\r\n}\r\n\r\n\r\n  /**************/\r\n /* サイドバー */\r\n/**************/\r\n.SideContainer { width: 124px; margin-right: 16px; }\r\n\r\n\r\n\r\n\r\n\r\n  /************/\r\n /* ニコレポ */\r\n/************/\r\n\r\n /* 各ニコレポのタイトルヘッダ部 */\r\n/* 投稿者欄の縦幅縮小 (original: 40px) */\r\n.NicorepoItem-sender { height: 30px; }\r\n.NicorepoItem-senderIcon.Thumbnail { width: 30px; height: 30px; }\r\n\r\n\r\n /* 各ニコレポのコンテンツ部 */\r\n/* コンテンツ部のインデント縮小 (original: 40px) */\r\n.NicorepoItem-body { margin-left: 20px; }\r\n\r\n\r\n /* サムネ関連 */\r\n/* サムネ本体の縮小  (original: 112 x 63) */\r\n.NicorepoItem-contentThumbnailImage.Thumbnail { width: 78px; height: 46px; }\r\n\r\n\r\n /* サムネ位置関連 */\r\n/* サムネを左端に、文章をその右にするための整形 */\r\n.NicorepoItem-activity {\r\n    margin-top: 4px;\r\n    margin-bottom: 4px;\r\n    font-size: 14px;\r\n    margin-left: 84px   /* サムネ本体 + 6px分右に避ける */;\r\n}\r\n.NicorepoItem-contentThumbnail { bottom: 1em; }  /* サムネ本体を1行分上に */\r\n.NicorepoItem-content { margin-bottom: -1em; }  /* もともとサムネのあった場所にまで次のコンテンツを詰める */\r\n\r\n\r\n\r\n /* タイトル周り */\r\n/* コンテンツ名のサイズ */\r\n.NicorepoItem-contentDetailTitle { font-size: 16px; }\r\n\r\n/* コンテンツ種別アイコンとコンテンツ名をインライン表示 */\r\n.NicorepoItem-contentDetail, .NicorepoItem-contentDetailLabel, .NicorepoItem-contentDetailTitle { display: inline; }\r\n.NicorepoItem-contentDetailTitle { margin-left: 4px; }\r\n\r\n\r\n\r\n\r\n\r\n  /*************************/\r\n /* あとで見る/マイリスト */\r\n/*************************/\r\n/* ヘッダと各アイテム詰め詰め */\r\n.WatchLaterContainer-header { margin-bottom: 4px; }\r\n.WatchLaterList-item.WatchLaterListItem { padding-top: 4px; }\r\n\r\n/* サムネ(original: 192 x 108) */\r\n.VideoMediaObject-thumbnail { width: 96px; height: 54px; }\r\n/* サムネ縮小に伴うMetadata/Checkboxレイアウト崩壊の修正 */\r\n.VideoMediaObject-bodyDescription { margin-bottom: 2em; }\r\n.CheckboxVideoMediaObject-checkboxArea { margin-top: 16px; }  /* original: 42px */\r\n\r\n/* 投稿日と再生数カウンタのインライン化 */\r\n.VideoMetaData-video, .VideoMetaData-count {\r\n    display: inline-block;\r\n    margin-right: 12px;\r\n    vertical-align: top;\r\n}\r\n\r\n/* マイリス登録日を右寄せにして2行分上に詰める*/\r\n.MylistItemAddition, .WatchLaterListItem-addition {\r\n    position: relative;\r\n    margin-top: 6px;\r\n    bottom: 2em;\r\n    margin-bottom: -2em;\r\n}\r\n.MylistItemAddition-row { justify-content: flex-end; height: 24px; }\r\n\r\n\r\n\r\n\r\n  /********/\r\n /* 履歴 */\r\n/********/\r\n/* ヘッダと各アイテム詰め詰め */\r\n.VideoWatchHistoryContainer-header { margin-bottom: 1em; }\r\n.VideoWatchHistoryContainer-editMenu { margin-bottom: 4px; }\r\n.VideoWatchHistoryContainer-item { padding: 4px; }\r\n\r\n/* 視聴日を右寄せにしていい感じに上に詰める */\r\n.VideoWatchHistoryItemAfter span { margin-left: 10px; font-size: 12px; }\r\n.VideoLabels { display: inline; }   /* [CH] のようなラベルがflexのままだと次行に落ちるのでインライン化 */\r\n\r\n.VideoWatchHistoryItemAfter {\r\n    position: relative;\r\n    margin-top: 0;\r\n    justify-content: flex-end;\r\n    bottom: 2em; /* XXX: bottomとmargin-bottomを揃えられないか？ */;\r\n}\r\n.VideoWatchHistoryContainer-item { margin-bottom: -1.3em; }\r\n}",
  "discussions": [],
  "discussionsCount": 0,
  "commentsCount": 0,
  "userjs_url": "/styles/userjs/191488/re-2020-10.user.js",
  "style_settings": []
}