{
  "id": 191437,
  "name": "Lolnadarks",
  "description": "Lolnada tema oscuro-Aguacate rancio versión 1.1",
  "user": {
    "id": 1055394,
    "name": "Tlacuache",
    "email": "redacted",
    "paypal_email": null,
    "homepage": null,
    "about": null,
    "license": null
  },
  "updated": "2020-10-27T01:23:43.000Z",
  "weekly_install_count": 4,
  "total_install_count": 4,
  "rating": null,
  "after_screenshot_name": "https://userstyles.org/style_screenshots/191437_after.jpeg?r=1603786024",
  "obsoleting_style_id": null,
  "obsoleting_style_name": null,
  "obsolete": 0,
  "admin_delete_reason_id": null,
  "obsoletion_message": null,
  "screenshots": null,
  "license": "publicdomain",
  "created": "2020-10-26T09:32:34.000Z",
  "category": "global",
  "raw_subcategory": null,
  "subcategory": null,
  "additional_info": "V 1.1- Corrección(cambio) de colores. Ya se pueden leer bien los greentexts y las letras perronas",
  "style_tags": [],
  "css": "/* i really want this to be global */\r\nbody{background-color:#000000;}\r\n    a,a:visited,#modal,h1,p,.subtitle,.body,#xf,.post_no,i,.imp,.det,.sel-arc,select,input,#text,#alert_message,h3,strong{color:#fff;}\r\n.boardlist a{border-top:3px solid #aed581;}\r\nhr,.clear,.mcd{background-color:#424242;border-color:#424242;}\r\n.exp,.exp::before,.reply,.img,.a,#alert_div,#modal{background-color:#424242;}\r\n.ca li>a .det, .la li>a{background:#424242;}\r\n.ca li,.det{background:#424242;}\r\n.titulo{color:#b61827;}\r\n.reply{border:#424242;border-radius:10px;}\r\n.post-image{border-radius:10px;}\r\n.blotter,.enlinea,.threads .thread,.thread-image{background:#6b9b37;border-color:#6b9b37;color:#fff;border-radius:10px;}\r\n.bottom,.col,.uns lb{background-color:#000000;}\r\n.post.reply.highlighted {\r\n    background:#524c00;\r\n    border-color:#524c00;}\r\n.quote{color:#8bc34a;}\r\n#rr{ background:#616161;}\r\ntextarea{color:#fff;}\r\n#updater a, .image_id>a, .lfl, .nuevas_resp, .subtitle>p a, .volarr a, a#mqr, span.omitted a{background:#6b9b37;}\r\n.reply,.intro,.board_image{border-radius:10px;}\r\n.intro time,span.heading{color:#f05545;}\r\n.omitted,.unimportant,li,.av,label,#seg{color:#aeaeae}\r\n.hxs{background:transparent;}\r\nform table tr th {background:#6b9b37;border:1px solid #387002;color:#fff;}\r\n#hnd,.nombre,.cerrar{background:#6b9b37;color:#fff;}\r\n.wbg { background:transparent;}\r\nnav{background: linear-gradient(135deg,rgba(66, 66, 66,1) 0,rgba(66, 66, 66,.9) 20%,rgba(66, 66, 66,1) 100%);\r\n    background: -moz-linear-gradient(-45deg,rgba(66, 66, 66,1) 0,rgba(66, 66, 66,.9) 20%,rgba(66, 66, 66,1) 100%);\r\n    background: -webkit-linear-gradient(-45deg,rgba(66, 66, 66,1) 0,rgba(66, 66, 66,.9) 20%,rgba(66, 66, 66,1) 100%);\r\n    }\r\n.fa-quote-right{color:#6b9b37;}\r\n.post.reply{background-color:#424242;}\r\n.intro {background-color:transparent;}\r\n.sel-arc, select {background-color:#6b9b37;}\r\n\r\n\r\n:after,:before {\r\n    -webkit-box-sizing: border-box;\r\n    -moz-box-sizing: border-box;\r\n    box-sizing: border-box\r\n}\r\n\r\n@media(max-width: 767px) {\r\n.post.reply .intro {\r\n    background-color:#387002;\r\n}\r\n.intro{border-radius:0;}\r\n.post-image{border-radius:10px;}\r\n}",
  "discussions": [],
  "discussionsCount": 0,
  "commentsCount": 0,
  "userjs_url": "/styles/userjs/191437/lolnadarks.user.js",
  "style_settings": []
}